vpredicto/__init__.py
vpredicto/main.py
vpredicto/API/BaseClass.py
vpredicto/API/BaseClassReda.py
vpredicto/API/__init__.py
vpredicto/Utils/__init__.py
vpredicto/Utils/utils.py
vpredicto/configs/__init__.py
vpredicto/configs/convlstm.py
vpredicto/configs/mim.py
vpredicto/models/CausalLSTM.py
vpredicto/models/ConvLSTM.py
vpredicto/models/GAN.py
vpredicto/models/MIM.py
vpredicto/models/PredNet.py
vpredicto/models/PredRNNPlusPlus.py
vpredicto/models/SimVP.py
vpredicto/models/__init__.py
vpredicto/modules/__init__.py
vpredicto/modules/convlstm/__init__.py
vpredicto/modules/convlstm/cell.py
vpredicto/modules/convlstm/conv.py
vpredicto/modules/gan/Discriminator.py
vpredicto/modules/gan/Generator.py
vpredicto/modules/gan/ResidualBlock.py
vpredicto/modules/gan/__init__.py
vpredicto/modules/mim/__init__.py
vpredicto/modules/mim/config.py
vpredicto/modules/mim/convig.py
vpredicto/modules/mim/mim.py
vpredicto/modules/mim/mimblock.py
vpredicto/modules/mim/mimn.py
vpredicto/modules/mim/stlstm.py
vpredicto/modules/prednet/__init__.py
vpredicto/modules/prednet/convlstm.py
vpredicto/modules/predrnnpp/__init__.py
vpredicto/modules/predrnnpp/causal_lstm.py
vpredicto/modules/predrnnpp/ghu.py
vpredicto/modules/simvp/Decoder.py
vpredicto/modules/simvp/Encoder.py
vpredicto/modules/simvp/Inception.py
vpredicto/modules/simvp/Translator.py
vpredicto/modules/simvp/__init__.py
vpredicto-0.2.1.dist-info/METADATA
vpredicto-0.2.1.dist-info/WHEEL
vpredicto-0.2.1.dist-info/top_level.txt
vpredicto-0.2.1.dist-info/RECORD
