Metadata-Version: 2.1
Name: vpredicto
Version: 0.2.1
Summary: A library for video frame prediction using SimVP, PredRNN++, MIM, PredNet, Novel GAN and Causal LSTM.
Home-page: https://github.com/karimsaqer/predicto
Author: Team 18
Author-email: Karim.Saqer01@eng-st.cu.edu.eg
Requires-Python: >=3.6
Requires-Dist: torch >=1.7.0
Requires-Dist: torchvision >=0.8.1
Requires-Dist: pytorch-lightning >=1.0.0
Requires-Dist: scikit-image >=0.17.2
Requires-Dist: numpy >=1.19.2
